django_admin_compare/__init__.py
django_admin_compare/admin.py
django_admin_compare/apps.py
django_admin_compare/templates/__init__.py
django_admin_compare/templates/list_compare.html
django_admin_compare-0.2.1.dist-info/METADATA
django_admin_compare-0.2.1.dist-info/WHEEL
django_admin_compare-0.2.1.dist-info/top_level.txt
django_admin_compare-0.2.1.dist-info/RECORD
