Metadata-Version: 2.1
Name: django-admin-compare
Version: 0.2.1
Summary: adds an action 'compare' to the admin panel on a page with a list of objects.
Home-page: https://github.com/meat-source/django-admin-compare
Author: Slava Ukolov
Author-email: ukolovsl88@gmail.com
License: UNKNOWN
Platform: UNKNOWN
Classifier: Programming Language :: Python :: 3
Classifier: License :: OSI Approved :: MIT License
Classifier: Operating System :: OS Independent
Requires-Python: >=3.4
